prefect_azure/__init__.py
prefect_azure/_version.py
prefect_azure/blob_storage.py
prefect_azure/container_instance.py
prefect_azure/cosmos_db.py
prefect_azure/credentials.py
prefect_azure/ml_datastore.py
prefect_azure/py.typed
prefect_azure/repository.py
prefect_azure/deployments/__init__.py
prefect_azure/deployments/steps.py
prefect_azure/experimental/__init__.py
prefect_azure/experimental/decorators.py
prefect_azure/experimental/bundles/__init__.py
prefect_azure/experimental/bundles/execute.py
prefect_azure/experimental/bundles/upload.py
prefect_azure/workers/__init__.py
prefect_azure/workers/container_instance.py
prefect_azure-0.4.7.dist-info/licenses/LICENSE
prefect_azure-0.4.7.dist-info/METADATA
prefect_azure-0.4.7.dist-info/WHEEL
prefect_azure-0.4.7.dist-info/entry_points.txt
prefect_azure-0.4.7.dist-info/top_level.txt
prefect_azure-0.4.7.dist-info/RECORD
